{
	"inst": "trombone",
	"note": "f4",
	"fundfreq": 349.228,
	"harmonics": [
		{
			"num": 1,
			"freq": 349.228,
			"amp": 1942.73902,
			"db": -7.22814,
			"phase": 2.36931
		},
		{
			"num": 2,
			"freq": 698.456,
			"amp": 4465.0,
			"db": 0.00000,
			"phase": 1.52870
		},
		{
			"num": 3,
			"freq": 1047.684,
			"amp": 2520.87008,
			"db": -4.96542,
			"phase": -0.30725
		},
		{
			"num": 4,
			"freq": 1396.912,
			"amp": 1270.28586,
			"db": -10.91840,
			"phase": -2.08679
		},
		{
			"num": 5,
			"freq": 1746.14,
			"amp": 500.618,
			"db": -19.00630,
			"phase": 2.82413
		},
		{
			"num": 6,
			"freq": 2095.368,
			"amp": 257.72198,
			"db": -24.77340,
			"phase": 1.75060
		},
		{
			"num": 7,
			"freq": 2444.596,
			"amp": 127.51359,
			"db": -30.88530,
			"phase": 0.45976
		},
		{
			"num": 8,
			"freq": 2793.824,
			"amp": 46.1266,
			"db": -39.71740,
			"phase": -0.51978
		},
		{
			"num": 9,
			"freq": 3143.052,
			"amp": 18.97084,
			"db": -47.43470,
			"phase": -1.44315
		},
		{
			"num": 10,
			"freq": 3492.28,
			"amp": 3.2106,
			"db": -62.86470,
			"phase": 1.88495
		},
		{
			"num": 11,
			"freq": 3841.508,
			"amp": 3.27794,
			"db": -62.68440,
			"phase": 1.42191
		},
		{
			"num": 12,
			"freq": 4190.736,
			"amp": 1.16464,
			"db": -71.67260,
			"phase": -1.26606
		},
		{
			"num": 13,
			"freq": 4539.964,
			"amp": 2.52541,
			"db": -64.94980,
			"phase": -2.76670
		},
		{
			"num": 14,
			"freq": 4889.192,
			"amp": 3.38822,
			"db": -62.39700,
			"phase": 3.10221
		},
		{
			"num": 15,
			"freq": 5238.42,
			"amp": 3.00934,
			"db": -63.42700,
			"phase": 2.85724
		},
		{
			"num": 16,
			"freq": 5587.648,
			"amp": 1.0859,
			"db": -72.28060,
			"phase": -2.29505
		},
		{
			"num": 17,
			"freq": 5936.876,
			"amp": 0.12308,
			"db": -91.19270,
			"phase": -2.57971
		},
		{
			"num": 18,
			"freq": 6286.104,
			"amp": 1.68823,
			"db": -68.44780,
			"phase": 0.61674
		},
		{
			"num": 19,
			"freq": 6635.332,
			"amp": 2.18984,
			"db": -66.18820,
			"phase": 0.07190
		},
		{
			"num": 20,
			"freq": 6984.56,
			"amp": 2.72077,
			"db": -64.30260,
			"phase": -0.48216
		},
		{
			"num": 21,
			"freq": 7333.788,
			"amp": 2.92147,
			"db": -63.68440,
			"phase": -0.72893
		},
		{
			"num": 22,
			"freq": 7683.016,
			"amp": 1.50164,
			"db": -69.46510,
			"phase": 0.54336
		},
		{
			"num": 23,
			"freq": 8032.244,
			"amp": 2.52375,
			"db": -64.95550,
			"phase": -2.10853
		},
		{
			"num": 24,
			"freq": 8381.472,
			"amp": 1.11558,
			"db": -72.04640,
			"phase": 2.55909
		},
		{
			"num": 25,
			"freq": 8730.7,
			"amp": 0.83865,
			"db": -74.52480,
			"phase": -1.36961
		},
		{
			"num": 26,
			"freq": 9079.928,
			"amp": 1.53772,
			"db": -69.25890,
			"phase": -2.55768
		},
		{
			"num": 27,
			"freq": 9429.156,
			"amp": 0.94165,
			"db": -73.51860,
			"phase": -2.90659
		},
		{
			"num": 28,
			"freq": 9778.384,
			"amp": 0.93646,
			"db": -73.56660,
			"phase": 0.85734
		}
	]
}
