{
	"inst": "C_trumpet_muted",
	"note": "c5",
	"fundfreq": 523.251,
	"harmonics": [
		{
			"num": 1,
			"freq": 523.251,
			"amp": 365.96621,
			"db": -11.02340,
			"phase": 2.99212
		},
		{
			"num": 2,
			"freq": 1046.502,
			"amp": 240.62236,
			"db": -14.66550,
			"phase": 1.98125
		},
		{
			"num": 3,
			"freq": 1569.753,
			"amp": 166.10243,
			"db": -17.88470,
			"phase": 2.67620
		},
		{
			"num": 4,
			"freq": 2093.004,
			"amp": 204.50361,
			"db": -16.07820,
			"phase": -0.24231
		},
		{
			"num": 5,
			"freq": 2616.255,
			"amp": 247.31815,
			"db": -14.42710,
			"phase": -0.54500
		},
		{
			"num": 6,
			"freq": 3139.506,
			"amp": 303.28853,
			"db": -12.65510,
			"phase": -2.78285
		},
		{
			"num": 7,
			"freq": 3662.757,
			"amp": 483.64977,
			"db": -8.60160,
			"phase": 0.35682
		},
		{
			"num": 8,
			"freq": 4186.008,
			"amp": 82.69914,
			"db": -23.94220,
			"phase": -1.68469
		},
		{
			"num": 9,
			"freq": 4709.259,
			"amp": 409.8038,
			"db": -10.04070,
			"phase": -0.48144
		},
		{
			"num": 10,
			"freq": 5232.51,
			"amp": 768.0659,
			"db": -4.58425,
			"phase": 1.20240
		},
		{
			"num": 11,
			"freq": 5755.761,
			"amp": 201.10413,
			"db": -16.22380,
			"phase": 2.13503
		},
		{
			"num": 12,
			"freq": 6279.012,
			"amp": 1026.27319,
			"db": -2.06696,
			"phase": -0.61696
		},
		{
			"num": 13,
			"freq": 6802.263,
			"amp": 138.65674,
			"db": -19.45340,
			"phase": 2.36322
		},
		{
			"num": 14,
			"freq": 7325.514,
			"amp": 1302.0,
			"db": 0.00000,
			"phase": 1.10781
		},
		{
			"num": 15,
			"freq": 7848.765,
			"amp": 412.80028,
			"db": -9.97742,
			"phase": -1.97793
		},
		{
			"num": 16,
			"freq": 8372.016,
			"amp": 334.92764,
			"db": -11.79320,
			"phase": -2.79150
		},
		{
			"num": 17,
			"freq": 8895.267,
			"amp": 171.56788,
			"db": -17.60350,
			"phase": 0.35842
		},
		{
			"num": 18,
			"freq": 9418.518,
			"amp": 136.29219,
			"db": -19.60280,
			"phase": 2.07472
		},
		{
			"num": 19,
			"freq": 9941.769,
			"amp": 326.32172,
			"db": -12.01930,
			"phase": 0.32569
		}
	]
}
