{
	"inst": "C_trumpet_muted",
	"note": "f#4",
	"fundfreq": 369.994,
	"harmonics": [
		{
			"num": 1,
			"freq": 369.994,
			"amp": 1975.8822,
			"db": -0.90159,
			"phase": -1.97152
		},
		{
			"num": 2,
			"freq": 739.988,
			"amp": 540.22608,
			"db": -12.16530,
			"phase": -1.19767
		},
		{
			"num": 3,
			"freq": 1109.982,
			"amp": 375.70809,
			"db": -15.31980,
			"phase": -0.74073
		},
		{
			"num": 4,
			"freq": 1479.976,
			"amp": 166.21704,
			"db": -22.40330,
			"phase": 0.90907
		},
		{
			"num": 5,
			"freq": 1849.97,
			"amp": 680.50379,
			"db": -10.16020,
			"phase": -0.11251
		},
		{
			"num": 6,
			"freq": 2219.964,
			"amp": 331.65424,
			"db": -16.40310,
			"phase": -0.83100
		},
		{
			"num": 7,
			"freq": 2589.958,
			"amp": 165.16976,
			"db": -22.45820,
			"phase": 1.08266
		},
		{
			"num": 8,
			"freq": 2959.952,
			"amp": 560.88723,
			"db": -11.83930,
			"phase": 0.79534
		},
		{
			"num": 9,
			"freq": 3329.946,
			"amp": 915.83461,
			"db": -7.58047,
			"phase": 0.27130
		},
		{
			"num": 10,
			"freq": 3699.94,
			"amp": 512.50788,
			"db": -12.62280,
			"phase": -0.84037
		},
		{
			"num": 11,
			"freq": 4069.934,
			"amp": 247.67122,
			"db": -18.93930,
			"phase": -0.98923
		},
		{
			"num": 12,
			"freq": 4439.928,
			"amp": 21.00079,
			"db": -40.37210,
			"phase": 1.08286
		},
		{
			"num": 13,
			"freq": 4809.922,
			"amp": 582.61351,
			"db": -11.50920,
			"phase": 1.27708
		},
		{
			"num": 14,
			"freq": 5179.916,
			"amp": 2192.0,
			"db": 0.00000,
			"phase": -0.54158
		},
		{
			"num": 15,
			"freq": 5549.91,
			"amp": 131.37888,
			"db": -24.44630,
			"phase": -1.97828
		},
		{
			"num": 16,
			"freq": 5919.904,
			"amp": 367.84559,
			"db": -15.50350,
			"phase": 0.26656
		},
		{
			"num": 17,
			"freq": 6289.898,
			"amp": 1136.23601,
			"db": -5.70744,
			"phase": 0.27939
		},
		{
			"num": 18,
			"freq": 6659.892,
			"amp": 1248.31891,
			"db": -4.89030,
			"phase": -1.00005
		},
		{
			"num": 19,
			"freq": 7029.886,
			"amp": 918.52092,
			"db": -7.55503,
			"phase": -0.60298
		},
		{
			"num": 20,
			"freq": 7399.88,
			"amp": 1429.83542,
			"db": -3.71109,
			"phase": -1.73182
		},
		{
			"num": 21,
			"freq": 7769.874,
			"amp": 1195.13661,
			"db": -5.26846,
			"phase": -2.52596
		},
		{
			"num": 22,
			"freq": 8139.868,
			"amp": 329.38252,
			"db": -16.46280,
			"phase": -1.57001
		},
		{
			"num": 23,
			"freq": 8509.862,
			"amp": 324.63142,
			"db": -16.58900,
			"phase": -2.85128
		},
		{
			"num": 24,
			"freq": 8879.856,
			"amp": 257.46343,
			"db": -18.60250,
			"phase": 2.58716
		},
		{
			"num": 25,
			"freq": 9249.85,
			"amp": 496.86745,
			"db": -12.89200,
			"phase": 0.50717
		},
		{
			"num": 26,
			"freq": 9619.844,
			"amp": 205.66034,
			"db": -20.55380,
			"phase": 0.04618
		},
		{
			"num": 27,
			"freq": 9989.838,
			"amp": 219.7888,
			"db": -19.97670,
			"phase": -1.03007
		}
	]
}
