{
	"inst": "bass_clarinet",
	"note": "b3",
	"fundfreq": 246.942,
	"harmonics": [
		{
			"num": 1,
			"freq": 246.942,
			"amp": 4774.0,
			"db": 0.00000,
			"phase": -1.64510
		},
		{
			"num": 2,
			"freq": 493.884,
			"amp": 112.48702,
			"db": -32.55560,
			"phase": -0.14943
		},
		{
			"num": 3,
			"freq": 740.826,
			"amp": 111.29801,
			"db": -32.64790,
			"phase": 3.14079
		},
		{
			"num": 4,
			"freq": 987.768,
			"amp": 241.35284,
			"db": -25.92460,
			"phase": 1.58200
		},
		{
			"num": 5,
			"freq": 1234.71,
			"amp": 1496.20952,
			"db": -10.07780,
			"phase": -0.05849
		},
		{
			"num": 6,
			"freq": 1481.652,
			"amp": 350.24135,
			"db": -22.69030,
			"phase": -0.01288
		},
		{
			"num": 7,
			"freq": 1728.594,
			"amp": 363.13024,
			"db": -22.37640,
			"phase": 2.21454
		},
		{
			"num": 8,
			"freq": 1975.536,
			"amp": 398.412,
			"db": -21.57100,
			"phase": 2.85092
		},
		{
			"num": 9,
			"freq": 2222.478,
			"amp": 420.88884,
			"db": -21.09430,
			"phase": 2.58478
		},
		{
			"num": 10,
			"freq": 2469.42,
			"amp": 303.99568,
			"db": -23.92030,
			"phase": 2.74440
		},
		{
			"num": 11,
			"freq": 2716.362,
			"amp": 102.27451,
			"db": -33.38230,
			"phase": -2.50948
		},
		{
			"num": 12,
			"freq": 2963.304,
			"amp": 80.73139,
			"db": -35.43680,
			"phase": -1.55110
		},
		{
			"num": 13,
			"freq": 3210.246,
			"amp": 5.39352,
			"db": -58.94020,
			"phase": -1.49679
		},
		{
			"num": 14,
			"freq": 3457.188,
			"amp": 39.60203,
			"db": -41.62330,
			"phase": 1.34711
		},
		{
			"num": 15,
			"freq": 3704.13,
			"amp": 178.89056,
			"db": -28.52590,
			"phase": 1.57439
		},
		{
			"num": 16,
			"freq": 3951.072,
			"amp": 40.53381,
			"db": -41.42130,
			"phase": 0.78347
		},
		{
			"num": 17,
			"freq": 4198.014,
			"amp": 35.89859,
			"db": -42.47610,
			"phase": -1.13296
		},
		{
			"num": 18,
			"freq": 4444.956,
			"amp": 57.59469,
			"db": -38.37000,
			"phase": 2.92578
		},
		{
			"num": 19,
			"freq": 4691.898,
			"amp": 14.67616,
			"db": -50.24540,
			"phase": 1.89464
		},
		{
			"num": 20,
			"freq": 4938.84,
			"amp": 27.8819,
			"db": -44.67120,
			"phase": -0.13402
		},
		{
			"num": 21,
			"freq": 5185.782,
			"amp": 51.34905,
			"db": -39.36700,
			"phase": 2.73764
		},
		{
			"num": 22,
			"freq": 5432.724,
			"amp": 42.7152,
			"db": -40.96600,
			"phase": 0.29607
		},
		{
			"num": 23,
			"freq": 5679.666,
			"amp": 21.25873,
			"db": -47.02690,
			"phase": 2.78751
		},
		{
			"num": 24,
			"freq": 5926.608,
			"amp": 16.71947,
			"db": -49.11320,
			"phase": 3.00163
		},
		{
			"num": 25,
			"freq": 6173.55,
			"amp": 13.03774,
			"db": -51.27360,
			"phase": 2.36830
		},
		{
			"num": 26,
			"freq": 6420.492,
			"amp": 11.6056,
			"db": -52.28430,
			"phase": -1.80962
		},
		{
			"num": 27,
			"freq": 6667.434,
			"amp": 6.45821,
			"db": -57.37540,
			"phase": -1.71822
		},
		{
			"num": 28,
			"freq": 6914.376,
			"amp": 6.18141,
			"db": -57.75590,
			"phase": 2.48282
		},
		{
			"num": 29,
			"freq": 7161.318,
			"amp": 2.53377,
			"db": -65.50230,
			"phase": 1.58141
		},
		{
			"num": 30,
			"freq": 7408.26,
			"amp": 11.26127,
			"db": -52.54590,
			"phase": -2.39059
		},
		{
			"num": 31,
			"freq": 7655.202,
			"amp": 14.01191,
			"db": -50.64770,
			"phase": 2.67874
		},
		{
			"num": 32,
			"freq": 7902.144,
			"amp": 4.7701,
			"db": -60.00710,
			"phase": 1.52943
		},
		{
			"num": 33,
			"freq": 8149.086,
			"amp": 9.61518,
			"db": -53.91850,
			"phase": 2.75225
		},
		{
			"num": 34,
			"freq": 8396.028,
			"amp": 13.75347,
			"db": -50.80940,
			"phase": 1.47233
		},
		{
			"num": 35,
			"freq": 8642.97,
			"amp": 5.51426,
			"db": -58.74790,
			"phase": 0.98404
		},
		{
			"num": 36,
			"freq": 8889.912,
			"amp": 6.10264,
			"db": -57.86730,
			"phase": 1.14957
		},
		{
			"num": 37,
			"freq": 9136.854,
			"amp": 6.40977,
			"db": -57.44080,
			"phase": 0.02389
		},
		{
			"num": 38,
			"freq": 9383.796,
			"amp": 3.2005,
			"db": -63.47330,
			"phase": 1.13087
		},
		{
			"num": 39,
			"freq": 9630.738,
			"amp": 5.27937,
			"db": -59.12600,
			"phase": 0.95704
		},
		{
			"num": 40,
			"freq": 9877.68,
			"amp": 7.8165,
			"db": -55.71740,
			"phase": 0.16559
		}
	]
}
