{
	"inst": "Bach_trumpet",
	"note": "d#6",
	"fundfreq": 1244.51,
	"harmonics": [
		{
			"num": 1,
			"freq": 1244.51,
			"amp": 3371.39354,
			"db": -0.50204,
			"phase": 0.90557
		},
		{
			"num": 2,
			"freq": 2489.02,
			"amp": 3572.0,
			"db": 0.00000,
			"phase": 1.30366
		},
		{
			"num": 3,
			"freq": 3733.53,
			"amp": 1461.43314,
			"db": -7.76265,
			"phase": 0.78888
		},
		{
			"num": 4,
			"freq": 4978.04,
			"amp": 336.93913,
			"db": -20.50720,
			"phase": -0.02269
		},
		{
			"num": 5,
			"freq": 6222.55,
			"amp": 252.64543,
			"db": -23.00800,
			"phase": 1.16080
		},
		{
			"num": 6,
			"freq": 7467.06,
			"amp": 73.52101,
			"db": -33.73000,
			"phase": 2.55693
		},
		{
			"num": 7,
			"freq": 8711.57,
			"amp": 30.94151,
			"db": -41.24740,
			"phase": -1.59471
		}
	]
}
