{
	"inst": "alto_trombone",
	"note": "d5",
	"fundfreq": 587.33,
	"harmonics": [
		{
			"num": 1,
			"freq": 587.33,
			"amp": 4581.0,
			"db": 0.00000,
			"phase": -1.92220
		},
		{
			"num": 2,
			"freq": 1174.66,
			"amp": 2024.70517,
			"db": -7.09197,
			"phase": -1.27480
		},
		{
			"num": 3,
			"freq": 1761.99,
			"amp": 1116.45261,
			"db": -12.26240,
			"phase": -1.27566
		},
		{
			"num": 4,
			"freq": 2349.32,
			"amp": 343.42768,
			"db": -22.50250,
			"phase": -0.52765
		},
		{
			"num": 5,
			"freq": 2936.65,
			"amp": 185.32341,
			"db": -27.86060,
			"phase": 0.46872
		},
		{
			"num": 6,
			"freq": 3523.98,
			"amp": 56.42873,
			"db": -38.18920,
			"phase": 0.92560
		},
		{
			"num": 7,
			"freq": 4111.31,
			"amp": 26.12374,
			"db": -44.87850,
			"phase": 2.50895
		},
		{
			"num": 8,
			"freq": 4698.64,
			"amp": 10.23718,
			"db": -53.01560,
			"phase": 1.93406
		},
		{
			"num": 9,
			"freq": 5285.97,
			"amp": 2.57324,
			"db": -65.00960,
			"phase": 1.04197
		},
		{
			"num": 10,
			"freq": 5873.3,
			"amp": 12.29024,
			"db": -51.42800,
			"phase": -2.68866
		},
		{
			"num": 11,
			"freq": 6460.63,
			"amp": 8.67502,
			"db": -54.45380,
			"phase": -0.65929
		},
		{
			"num": 12,
			"freq": 7047.96,
			"amp": 1.87431,
			"db": -67.76240,
			"phase": 0.77520
		},
		{
			"num": 13,
			"freq": 7635.29,
			"amp": 6.19014,
			"db": -57.38520,
			"phase": 0.56834
		},
		{
			"num": 14,
			"freq": 8222.62,
			"amp": 4.16122,
			"db": -60.83480,
			"phase": 0.66263
		},
		{
			"num": 15,
			"freq": 8809.95,
			"amp": 2.53563,
			"db": -65.13750,
			"phase": 3.02573
		},
		{
			"num": 16,
			"freq": 9397.28,
			"amp": 5.20595,
			"db": -58.88920,
			"phase": -2.35954
		},
		{
			"num": 17,
			"freq": 9984.61,
			"amp": 3.89332,
			"db": -61.41280,
			"phase": -1.83722
		}
	]
}
